{
  "updatedAtMs": 1770602422628,
  "updatedAt": "2026-02-09T02:00:22.628Z",
  "date": "2026-02-09",
  "wallet": "0xa668ddf22a4c0ecbb31c89b16f355b26ae7703c3",
  "basescan": "https://basescan.org/address/0xa668ddf22a4c0ecbb31c89b16f355b26ae7703c3",
  "rows": [
    {
      "symbol": "AntiHunter",
      "token": "0xe2f3fae4bc62e21826018364aa30ae45d430bb07",
      "balance": "2399999999.999980182207762571",
      "entryDate": "2026-02-06",
      "costBasisUsd": 0,
      "costBasisEth": "0",
      "fmvUsd": 130127.99999999891,
      "pnlUsd": 130127.99999999891
    },
    {
      "symbol": "WETH",
      "token": "0x4200000000000000000000000000000000000006",
      "balance": "18.077081312239105",
      "entryDate": "2026-02-06",
      "costBasisUsd": 0,
      "costBasisEth": "0",
      "fmvUsd": 37349.02154505459,
      "pnlUsd": 37349.02154505459
    },
    {
      "symbol": "BNKR",
      "token": "0x22af33fe49fd1fa80c7149773dde5890d3c76f3b",
      "balance": "10842315.643223245666320282",
      "entryDate": "2026-02-07",
      "costBasisUsd": 6288.9303,
      "costBasisEth": "3",
      "fmvUsd": 9765.673699851179,
      "pnlUsd": 3476.7433998511788
    },
    {
      "symbol": "bio",
      "token": "0xd655790b0486fa681c23b955f5ca7cd5f5c8cb07",
      "balance": "491617660.801773755517648542",
      "entryDate": "2026-02-07",
      "costBasisUsd": 2103.37898239,
      "costBasisEth": "1",
      "fmvUsd": 4621.206011536673,
      "pnlUsd": 2517.827029146673
    },
    {
      "symbol": "FELIX",
      "token": "0xf30bf00edd0c22db54c9274b90d2a4c21fc09b07",
      "balance": "234565737.063334765213666609",
      "entryDate": "2026-02-07",
      "costBasisUsd": 4192.6202,
      "costBasisEth": "2",
      "fmvUsd": 3323.7964941874534,
      "pnlUsd": -868.8237058125469
    },
    {
      "symbol": "ETH",
      "token": null,
      "balance": "0.9973581413337396",
      "entryDate": "2026-02-07",
      "costBasisUsd": 2066.098,
      "costBasisEth": "1",
      "fmvUsd": 2060.6396610933566,
      "pnlUsd": -5.458338906643348
    }
  ],
  "totalUsd": 187248.33741172217,
  "notes": [
    "Cost basis is inferred from on-chain ERC20 Transfer logs by pairing token in/out with WETH in/out within the same transaction.",
    "Native ETH swaps are partially inferred via tx.value only (internal ETH transfers are not captured).",
    "Airdrops/transfers without WETH/ETH flow are ignored for cost basis.",
    "Cost basis USD is estimated using Chainlink ETH/USD at the entry block when available (falls back to current ETH/USD)."
  ],
  "method": {
    "entryAndCostBasis": "derived-from-onchain-transfer-logs (token<->WETH pairing) with token allowlist; fee-derived $ANTIHUNTER and $WETH are hard-coded as entry=2026-02-06 and cost basis $0; ETH is hard-coded as entry=2026-02-07 with cost basis 1 ETH."
  }
}
